mcpgex/__init__.py
mcpgex/__main__.py
mcpgex/server.py
mseep_mcpgex-0.1.6.dist-info/METADATA
mseep_mcpgex-0.1.6.dist-info/WHEEL
mseep_mcpgex-0.1.6.dist-info/entry_points.txt
mseep_mcpgex-0.1.6.dist-info/licenses/LICENSE
mseep_mcpgex-0.1.6.dist-info/RECORD
